Metadata-Version: 2.1
Name: dnn-cool-losses
Version: 0.1.3
Summary: dnn_cool_losses: Per-sample loss functions and utilities
Home-page: https://github.com/hristo-vrigazov/dnn_cool_losses
Author: Hristo Vrigazov
Author-email: hvrigazov@gmail.com
License: MIT
Platform: UNKNOWN
Classifier: License :: OSI Approved :: MIT License
Classifier: Programming Language :: Python :: 3
Classifier: Programming Language :: Python :: 3.4
Classifier: Programming Language :: Python :: 3.5
Classifier: Programming Language :: Python :: 3.6
Classifier: Programming Language :: Python :: 3.7
Classifier: Programming Language :: Python :: 3.8
Classifier: Programming Language :: Python :: 3.9
Classifier: Operating System :: OS Independent
License-File: LICENSE
